{
  "versiculo": {
    "referencia": "Hebreos 9:27 Reina Valera 1960",
    "texto": "Y de la manera que está establecido para los hombres que mueran una sola vez, y después de esto el juicio,"
  },
  "analisisInterlineal": [
    {
      "numero": 1,
      "strongNumber": "2532",
      "texto": "καὶ",
      "transliteracion": "",
      "parsingLabel": "Conjunción",
      "parsing": "CONJ",
      "traduccion": "Y"
    },
    {
      "numero": 2,
      "strongNumber": "2596",
      "texto": "καθ’",
      "transliteracion": "",
      "parsingLabel": "Preposición",
      "parsing": "PREP",
      "traduccion": "según"
    },
    {
      "numero": 3,
      "strongNumber": "3745",
      "texto": "ὅσον",
      "transliteracion": "",
      "parsingLabel": "Pronombre Correlativo-Acusativo-Singular-Neutro",
      "parsing": "K-ASN",
      "traduccion": "tanto como"
    },
    {
      "numero": 4,
      "strongNumber": "606",
      "texto": "ἀπόκειται",
      "transliteracion": "",
      "parsingLabel": "Verbo-Presente-Deponente Medio o Pasivo-Indicativo-3ª Persona-Singular",
      "parsing": "V-PNI-3S",
      "traduccion": "está reservado"
    },
    {
      "numero": 5,
      "strongNumber": "3588",
      "texto": "τοῖς",
      "transliteracion": "",
      "parsingLabel": "Artículo-Dativo-Plural-Masculino",
      "parsing": "T-DPM",
      "traduccion": "a los"
    },
    {
      "numero": 6,
      "strongNumber": "444",
      "texto": "ἀνθρώποις",
      "transliteracion": "",
      "parsingLabel": "Sustantivo-Dativo-Plural-Masculino",
      "parsing": "N-DPM",
      "traduccion": "hombres"
    },
    {
      "numero": 7,
      "strongNumber": "530",
      "texto": "ἅπαξ",
      "transliteracion": "",
      "parsingLabel": "Adverbio",
      "parsing": "ADV",
      "traduccion": "una vez"
    },
    {
      "numero": 8,
      "strongNumber": "599",
      "texto": "ἀποθανεῖν,",
      "transliteracion": "",
      "parsingLabel": "Verbo-2º Aoristo-Activo-Infinitivo",
      "parsing": "V-2AAN",
      "traduccion": "morir"
    },
    {
      "numero": 9,
      "strongNumber": "3326",
      "texto": "μετὰ",
      "transliteracion": "",
      "parsingLabel": "Preposición",
      "parsing": "PREP",
      "traduccion": "después"
    },
    {
      "numero": 10,
      "strongNumber": "1161",
      "texto": "δὲ",
      "transliteracion": "",
      "parsingLabel": "Conjunción",
      "parsing": "CONJ",
      "traduccion": "pero"
    },
    {
      "numero": 11,
      "strongNumber": "3778",
      "texto": "τοῦτο",
      "transliteracion": "",
      "parsingLabel": "Pronombre Demostrativo-Acusativo-Singular-Neutro",
      "parsing": "D-ASN",
      "traduccion": "a esto"
    },
    {
      "numero": 12,
      "strongNumber": "2920",
      "texto": "κρίσις,",
      "transliteracion": "",
      "parsingLabel": "Sustantivo-Nominativo-Singular-Femenino",
      "parsing": "N-NSF",
      "traduccion": "juicio"
    }
  ]
}