{
  "versiculo": {
    "referencia": "1ra Reyes 18:46 Reina Valera 1960",
    "texto": "Y la mano de Jehová estuvo sobre Elías, el cual ciñó sus lomos, y corrió delante de Acab hasta llegar a Jezreel."
  },
  "analisisInterlineal": [
    {
      "numero": 1,
      "strongNumber": "9005",
      "hebreo": "וְ",
      "transliteracion": "וְ",
      "parsingLabel": "conjunción",
      "parsing": "CONJ",
      "traduccion": "y"
    },
    {
      "numero": 2,
      "strongNumber": "3027",
      "hebreo": "יָד",
      "transliteracion": "יַד־",
      "parsingLabel": "sustantivo desconocido singular constructivo",
      "parsing": "SUBS.U.SG.C",
      "traduccion": "(la)mano de"
    },
    {
      "numero": 3,
      "strongNumber": "3068",
      "hebreo": "יְהוָה",
      "transliteracion": "יְהוָ֗ה",
      "parsingLabel": "nombre propio masculino singular absoluto",
      "parsing": "NMPR.M.SG.A",
      "traduccion": "Yahweh"
    },
    {
      "numero": 4,
      "strongNumber": "1961",
      "hebreo": "היה",
      "transliteracion": "הָֽיְתָה֙",
      "parsingLabel": "verbo qal perfecto 3ª persona femenino singular",
      "parsing": "VERBO.QAL.PERF.P3.F.SG",
      "traduccion": "estuvo"
    },
    {
      "numero": 5,
      "strongNumber": "413",
      "hebreo": "אֶל",
      "transliteracion": "אֶל־",
      "parsingLabel": "preposición",
      "parsing": "PREP",
      "traduccion": "sobre"
    },
    {
      "numero": 6,
      "strongNumber": "452",
      "hebreo": "אֵלִיָּהוּ",
      "transliteracion": "אֵ֣לִיָּ֔הוּ",
      "parsingLabel": "nombre propio masculino singular absoluto",
      "parsing": "NMPR.M.SG.A",
      "traduccion": "Elías"
    },
    {
      "numero": 7,
      "strongNumber": "9005",
      "hebreo": "וְ",
      "transliteracion": "וַ",
      "parsingLabel": "conjunción",
      "parsing": "CONJ",
      "traduccion": "y"
    },
    {
      "numero": 8,
      "strongNumber": "8151",
      "hebreo": "שׁנס",
      "transliteracion": "יְשַׁנֵּ֖ס",
      "parsingLabel": "verbo pi“el wayyiqtol 3ª persona masculino singular",
      "parsing": "VERBO.PIEL.WAYQ.P3.M.SG",
      "traduccion": "se ciñó"
    },
    {
      "numero": 9,
      "strongNumber": "4975",
      "hebreo": "מָתְנַיִם",
      "transliteracion": "מָתְנָ֑יו",
      "parsingLabel": "sustantivo masculino dual absoluto pronominal sufijo 3ª persona masculino singular",
      "parsing": "SUBS.M.DU.A.PRS.P3.M.SG",
      "traduccion": "sus lomos"
    },
    {
      "numero": 10,
      "strongNumber": "9005",
      "hebreo": "וְ",
      "transliteracion": "וַ",
      "parsingLabel": "conjunción",
      "parsing": "CONJ",
      "traduccion": "y"
    },
    {
      "numero": 11,
      "strongNumber": "7323",
      "hebreo": "רוץ",
      "transliteracion": "יָּ֨רָץ֙",
      "parsingLabel": "verbo qal wayyiqtol 3ª persona masculino singular",
      "parsing": "VERBO.QAL.WAYQ.P3.M.SG",
      "traduccion": "corrió"
    },
    {
      "numero": 12,
      "strongNumber": "9003",
      "hebreo": "לְ",
      "transliteracion": "לִ",
      "parsingLabel": "preposición",
      "parsing": "PREP",
      "traduccion": "a"
    },
    {
      "numero": 13,
      "strongNumber": "6440",
      "hebreo": "פָּנֶה",
      "transliteracion": "פְנֵ֣י",
      "parsingLabel": "sustantivo masculino plural constructivo",
      "parsing": "SUBS.M.PL.C",
      "traduccion": "ante"
    },
    {
      "numero": 14,
      "strongNumber": "256",
      "hebreo": "אַחְאָב",
      "transliteracion": "אַחְאָ֔ב",
      "parsingLabel": "nombre propio masculino singular absoluto",
      "parsing": "NMPR.M.SG.A",
      "traduccion": "Acab"
    },
    {
      "numero": 15,
      "strongNumber": "5704",
      "hebreo": "עַד",
      "transliteracion": "עַד־",
      "parsingLabel": "preposición",
      "parsing": "PREP",
      "traduccion": "hasta"
    },
    {
      "numero": 16,
      "strongNumber": "935",
      "hebreo": "בוא",
      "transliteracion": "בֹּאֲכָ֖ה",
      "parsingLabel": "verbo qal infinitivo (construct) desconocido desconocido desconocido absoluto pronominal sufijo 2ª persona masculino singular",
      "parsing": "VERBO.QAL.INFC.U.U.U.A.PRS.P2.M.SG",
      "traduccion": "tu llegar"
    },
    {
      "numero": 17,
      "strongNumber": "3157",
      "hebreo": "יִזְרְעֶאל",
      "transliteracion": "יִזְרְעֶֽאלָה׃",
      "parsingLabel": "nombre propio desconocido singular absoluto",
      "parsing": "NMPR.U.SG.A",
      "traduccion": "a Jizreel"
    }
  ]
}