{
  "versiculo": {
    "referencia": "2da Reyes 24:14 Reina Valera 1960",
    "texto": "Y llevó en cautiverio a toda Jerusalén, a todos los príncipes, y a todos los hombres valientes, hasta diez mil cautivos, y a todos los artesanos y herreros; no quedó nadie, excepto los pobres del pueblo de la tierra."
  },
  "analisisInterlineal": [
    {
      "numero": 1,
      "strongNumber": "9005",
      "hebreo": "וְ",
      "transliteracion": "וְ",
      "parsingLabel": "conjunción",
      "parsing": "CONJ",
      "traduccion": "y"
    },
    {
      "numero": 2,
      "strongNumber": "1540",
      "hebreo": "גלה",
      "transliteracion": "הִגְלָ֣ה",
      "parsingLabel": "verbo hif‘il perfecto 3ª persona masculino singular",
      "parsing": "VERBO.HIF.PERF.P3.M.SG",
      "traduccion": "deportó"
    },
    {
      "numero": 3,
      "strongNumber": "853",
      "hebreo": "אֵת",
      "transliteracion": "אֶת־",
      "parsingLabel": "preposición",
      "parsing": "PREP",
      "traduccion": "a"
    },
    {
      "numero": 4,
      "strongNumber": "3605",
      "hebreo": "כֹּל",
      "transliteracion": "כָּל־",
      "parsingLabel": "sustantivo masculino singular constructivo",
      "parsing": "SUBS.M.SG.C",
      "traduccion": "todo"
    },
    {
      "numero": 5,
      "strongNumber": "3389",
      "hebreo": "יְרוּשָׁלִַם",
      "transliteracion": "יְ֠רוּשָׁלִַם",
      "parsingLabel": "nombre propio desconocido singular absoluto",
      "parsing": "NMPR.U.SG.A",
      "traduccion": "Jerusalén"
    },
    {
      "numero": 6,
      "strongNumber": "9005",
      "hebreo": "וְ",
      "transliteracion": "וְֽ",
      "parsingLabel": "conjunción",
      "parsing": "CONJ",
      "traduccion": "y"
    },
    {
      "numero": 7,
      "strongNumber": "853",
      "hebreo": "אֵת",
      "transliteracion": "אֶת־",
      "parsingLabel": "preposición",
      "parsing": "PREP",
      "traduccion": "a"
    },
    {
      "numero": 8,
      "strongNumber": "3605",
      "hebreo": "כֹּל",
      "transliteracion": "כָּל־",
      "parsingLabel": "sustantivo masculino singular constructivo",
      "parsing": "SUBS.M.SG.C",
      "traduccion": "todos"
    },
    {
      "numero": 9,
      "strongNumber": "9006",
      "hebreo": "הַ",
      "transliteracion": "הַ",
      "parsingLabel": "artículo",
      "parsing": "ART",
      "traduccion": "los"
    },
    {
      "numero": 10,
      "strongNumber": "8269",
      "hebreo": "שַׂר",
      "transliteracion": "שָּׂרִ֞ים",
      "parsingLabel": "sustantivo masculino plural absoluto",
      "parsing": "SUBS.M.PL.A",
      "traduccion": "oficiales"
    },
    {
      "numero": 11,
      "strongNumber": "9005",
      "hebreo": "וְ",
      "transliteracion": "וְ",
      "parsingLabel": "conjunción",
      "parsing": "CONJ",
      "traduccion": "y"
    },
    {
      "numero": 12,
      "strongNumber": "853",
      "hebreo": "אֵת",
      "transliteracion": "אֵ֣ת׀",
      "parsingLabel": "preposición",
      "parsing": "PREP",
      "traduccion": "a"
    },
    {
      "numero": 13,
      "strongNumber": "3605",
      "hebreo": "כֹּל",
      "transliteracion": "כָּל־",
      "parsingLabel": "sustantivo masculino singular constructivo",
      "parsing": "SUBS.M.SG.C",
      "traduccion": "todos"
    },
    {
      "numero": 14,
      "strongNumber": "1368",
      "hebreo": "גִּבֹּור",
      "transliteracion": "גִּבֹּורֵ֣י",
      "parsingLabel": "sustantivo masculino plural constructivo",
      "parsing": "SUBS.M.PL.C",
      "traduccion": "los héroes de"
    },
    {
      "numero": 15,
      "strongNumber": "9006",
      "hebreo": "הַ",
      "transliteracion": "הַ",
      "parsingLabel": "artículo",
      "parsing": "ART",
      "traduccion": "el"
    },
    {
      "numero": 16,
      "strongNumber": "2428",
      "hebreo": "חַיִל",
      "transliteracion": "חַ֗יִל",
      "parsingLabel": "sustantivo masculino singular absoluto",
      "parsing": "SUBS.M.SG.A",
      "traduccion": "valor"
    },
    {
      "numero": 17,
      "strongNumber": "6235",
      "hebreo": "עֲשָׂרָה",
      "transliteracion": "עֲשֶׂ֤רֶת",
      "parsingLabel": "sustantivo femenino singular constructivo",
      "parsing": "SUBS.F.SG.C",
      "traduccion": "diez"
    },
    {
      "numero": 18,
      "strongNumber": "505",
      "hebreo": "אֶלֶף",
      "transliteracion": "אֲלָפִים֙",
      "parsingLabel": "sustantivo masculino plural absoluto",
      "parsing": "SUBS.M.PL.A",
      "traduccion": "millares"
    },
    {
      "numero": 19,
      "strongNumber": "1540",
      "hebreo": "גלה",
      "transliteracion": "גֹּולֶ֔ה",
      "parsingLabel": "sustantivo qal participio desconocido masculino singular absoluto",
      "parsing": "SUBS.QAL.PTCA.U.M.SG.A",
      "traduccion": "deportados"
    },
    {
      "numero": 20,
      "strongNumber": "9005",
      "hebreo": "וְ",
      "transliteracion": "וְ",
      "parsingLabel": "conjunción",
      "parsing": "CONJ",
      "traduccion": "y"
    },
    {
      "numero": 21,
      "strongNumber": "3605",
      "hebreo": "כֹּל",
      "transliteracion": "כָל־",
      "parsingLabel": "sustantivo masculino singular constructivo",
      "parsing": "SUBS.M.SG.C",
      "traduccion": "nadie"
    },
    {
      "numero": 22,
      "strongNumber": "9006",
      "hebreo": "הַ",
      "transliteracion": "הֶ",
      "parsingLabel": "artículo",
      "parsing": "ART",
      "traduccion": "el"
    },
    {
      "numero": 23,
      "strongNumber": "2796",
      "hebreo": "חָרָשׁ",
      "transliteracion": "חָרָ֖שׁ",
      "parsingLabel": "sustantivo masculino singular absoluto",
      "parsing": "SUBS.M.SG.A",
      "traduccion": "artesano"
    },
    {
      "numero": 24,
      "strongNumber": "9005",
      "hebreo": "וְ",
      "transliteracion": "וְ",
      "parsingLabel": "conjunción",
      "parsing": "CONJ",
      "traduccion": "ni"
    },
    {
      "numero": 25,
      "strongNumber": "9006",
      "hebreo": "הַ",
      "transliteracion": "הַ",
      "parsingLabel": "artículo",
      "parsing": "ART",
      "traduccion": "el"
    },
    {
      "numero": 26,
      "strongNumber": "4525",
      "hebreo": "מַסְגֵּר",
      "transliteracion": "מַּסְגֵּ֑ר",
      "parsingLabel": "sustantivo masculino singular absoluto",
      "parsing": "SUBS.M.SG.A",
      "traduccion": "cerrajero"
    },
    {
      "numero": 27,
      "strongNumber": "3808",
      "hebreo": "לֹא",
      "transliteracion": "לֹ֣א",
      "parsingLabel": "negativo partículo",
      "parsing": "NEGA",
      "traduccion": "no"
    },
    {
      "numero": 28,
      "strongNumber": "7604",
      "hebreo": "שׁאר",
      "transliteracion": "נִשְׁאַ֔ר",
      "parsingLabel": "verbo nif‘al perfecto 3ª persona masculino singular",
      "parsing": "VERBO.NIF.PERF.P3.M.SG",
      "traduccion": "quedó"
    },
    {
      "numero": 29,
      "strongNumber": "2108",
      "hebreo": "זוּלָה",
      "transliteracion": "זוּלַ֖ת",
      "parsingLabel": "preposición femenino singular constructivo",
      "parsing": "PREP.F.SG.C",
      "traduccion": "fuera de"
    },
    {
      "numero": 30,
      "strongNumber": "1803",
      "hebreo": "דַּלָּה",
      "transliteracion": "דַּלַּ֥ת",
      "parsingLabel": "sustantivo femenino singular constructivo",
      "parsing": "SUBS.F.SG.C",
      "traduccion": "pobre de"
    },
    {
      "numero": 31,
      "strongNumber": "5971",
      "hebreo": "עַם",
      "transliteracion": "עַם־",
      "parsingLabel": "sustantivo masculino singular constructivo",
      "parsing": "SUBS.M.SG.C",
      "traduccion": "el pueblo de"
    },
    {
      "numero": 32,
      "strongNumber": "9006",
      "hebreo": "הַ",
      "transliteracion": "הָ",
      "parsingLabel": "artículo",
      "parsing": "ART",
      "traduccion": "la"
    },
    {
      "numero": 33,
      "strongNumber": "776",
      "hebreo": "אֶרֶץ",
      "transliteracion": "אָֽרֶץ׃",
      "parsingLabel": "sustantivo desconocido singular absoluto",
      "parsing": "SUBS.U.SG.A",
      "traduccion": "tierra"
    }
  ]
}