[
  {
    "cod": "2131",
    "palabraOrig": "זִיקָה",
    "pron": "zicá",
    "definicion": "prop. lo que salta hacia adelante, i.e. fogonazo de fuego, o flecha ardiente; también (del sentido orig. de la raíz) vínculo, lazo"
  },
  {
    "cod": "2132",
    "palabraOrig": "זַיִת",
    "pron": "záyit",
    "definicion": "olivo (como produciendo aceite para iluminación), el árbol, la rama o la aceituna"
  },
  {
    "cod": "2133",
    "palabraOrig": "זֵיתָן",
    "pron": "Zeitán",
    "definicion": "olivar; Zetán, un isr."
  },
  {
    "cod": "2134",
    "palabraOrig": "זַךְ",
    "pron": "zak",
    "definicion": "claro"
  },
  {
    "cod": "2135",
    "palabraOrig": "זָכָה",
    "pron": "zaká",
    "definicion": "ser translúcido; fig. ser inocente"
  },
  {
    "cod": "2136",
    "palabraOrig": "זָכוּ",
    "pron": "zakú",
    "definicion": "pureza"
  },
  {
    "cod": "2137",
    "palabraOrig": "זְכוּכִית",
    "pron": "zekukít",
    "definicion": "prop. transparencia, i.e. vidrio"
  },
  {
    "cod": "2138",
    "palabraOrig": "זָכוּר",
    "pron": "zakúr",
    "definicion": "macho (de hombre o animales)"
  },
  {
    "cod": "2139",
    "palabraOrig": "זַכּוּר",
    "pron": "Zakkúr",
    "definicion": "sensato; Zakur, nombre de siete isr."
  },
  {
    "cod": "2140",
    "palabraOrig": "זַכַּי",
    "pron": "Zakkái",
    "definicion": "puro; Zakai, un isr."
  }
]