{
  "versiculo": {
    "referencia": "Isaías 65:3 Reina Valera 1960",
    "texto": "pueblo que en mi rostro me provoca de continuo a ira, sacrificando en huertos, y quemando incienso sobre ladrillos;"
  },
  "analisisInterlineal": [
    {
      "numero": 1,
      "strongNumber": "9006",
      "hebreo": "הַ",
      "transliteracion": "הָ",
      "parsingLabel": "artículo",
      "parsing": "ART",
      "traduccion": "el"
    },
    {
      "numero": 2,
      "strongNumber": "5971",
      "hebreo": "עַם",
      "transliteracion": "עָ֗ם",
      "parsingLabel": "sustantivo masculino singular absoluto",
      "parsing": "SUBS.M.SG.A",
      "traduccion": "pueblo"
    },
    {
      "numero": 3,
      "strongNumber": "9006",
      "hebreo": "הַ",
      "transliteracion": "הַ",
      "parsingLabel": "conjunción",
      "parsing": "CONJ",
      "traduccion": "los"
    },
    {
      "numero": 4,
      "strongNumber": "3707",
      "hebreo": "כעס",
      "transliteracion": "מַּכְעִיסִ֥ים",
      "parsingLabel": "verbo hif‘il participio desconocido masculino plural absoluto",
      "parsing": "VERBO.HIF.PTCA.U.M.PL.A",
      "traduccion": "que provocan"
    },
    {
      "numero": 5,
      "strongNumber": "853",
      "hebreo": "אֵת",
      "transliteracion": "אֹותִ֛י",
      "parsingLabel": "preposición pronominal sufijo 1ª persona desconocido singular",
      "parsing": "PREP.PRS.P1.U.SG",
      "traduccion": "a mí"
    },
    {
      "numero": 6,
      "strongNumber": "5921",
      "hebreo": "עַל",
      "transliteracion": "עַל־",
      "parsingLabel": "preposición",
      "parsing": "PREP",
      "traduccion": "a"
    },
    {
      "numero": 7,
      "strongNumber": "6440",
      "hebreo": "פָּנֶה",
      "transliteracion": "פָּנַ֖י",
      "parsingLabel": "sustantivo masculino plural absoluto",
      "parsing": "SUBS.M.PL.A",
      "traduccion": "mi rostro"
    },
    {
      "numero": 8,
      "strongNumber": "8548",
      "hebreo": "תָּמִיד",
      "transliteracion": "תָּמִ֑יד",
      "parsingLabel": "adverbio masculino singular absoluto",
      "parsing": "ADVB.M.SG.A",
      "traduccion": "siemrpe"
    },
    {
      "numero": 9,
      "strongNumber": "2076",
      "hebreo": "זבח",
      "transliteracion": "זֹֽבְחִים֙",
      "parsingLabel": "verbo qal participio desconocido masculino plural absoluto",
      "parsing": "VERBO.QAL.PTCA.U.M.PL.A",
      "traduccion": "sacrifican"
    },
    {
      "numero": 10,
      "strongNumber": "9001",
      "hebreo": "בְּ",
      "transliteracion": "בַּ",
      "parsingLabel": "preposición",
      "parsing": "PREP",
      "traduccion": "en"
    },
    {
      "numero": 11,
      "strongNumber": "1593",
      "hebreo": "גַּנָּה",
      "transliteracion": "גַּנֹּ֔ות",
      "parsingLabel": "sustantivo femenino plural absoluto",
      "parsing": "SUBS.F.PL.A",
      "traduccion": "jardines"
    },
    {
      "numero": 12,
      "strongNumber": "9005",
      "hebreo": "וְ",
      "transliteracion": "וּֽ",
      "parsingLabel": "conjunción",
      "parsing": "CONJ",
      "traduccion": "y"
    },
    {
      "numero": 13,
      "strongNumber": "6999",
      "hebreo": "קטר",
      "transliteracion": "מְקַטְּרִ֖ים",
      "parsingLabel": "verbo pi“el participio desconocido masculino plural absoluto",
      "parsing": "VERBO.PIEL.PTCA.U.M.PL.A",
      "traduccion": "queman incienso"
    },
    {
      "numero": 14,
      "strongNumber": "5921",
      "hebreo": "עַל",
      "transliteracion": "עַל־",
      "parsingLabel": "preposición",
      "parsing": "PREP",
      "traduccion": "sobre"
    },
    {
      "numero": 15,
      "strongNumber": "9006",
      "hebreo": "הַ",
      "transliteracion": "הַ",
      "parsingLabel": "artículo",
      "parsing": "ART",
      "traduccion": "los"
    },
    {
      "numero": 16,
      "strongNumber": "3840",
      "hebreo": "לְבֵנָה",
      "transliteracion": "לְּבֵנִֽים׃",
      "parsingLabel": "sustantivo femenino plural absoluto",
      "parsing": "SUBS.F.PL.A",
      "traduccion": "ladrillos"
    }
  ]
}