{
  "versiculo": {
    "referencia": "Eclesiatés 3:5 Reina Valera 1960",
    "texto": "tiempo de esparcir piedras, y tiempo de juntar piedras; tiempo de abrazar, y tiempo de abstenerse de abrazar;"
  },
  "analisisInterlineal": [
    {
      "numero": 1,
      "strongNumber": "6256",
      "hebreo": "עֵת",
      "transliteracion": "עֵ֚ת",
      "parsingLabel": "sustantivo desconocido singular absoluto",
      "parsing": "SUBS.U.SG.A",
      "traduccion": "Tiempo"
    },
    {
      "numero": 2,
      "strongNumber": "9003",
      "hebreo": "לְ",
      "transliteracion": "לְ",
      "parsingLabel": "preposición",
      "parsing": "PREP",
      "traduccion": "para"
    },
    {
      "numero": 3,
      "strongNumber": "7993",
      "hebreo": "שׁלך",
      "transliteracion": "הַשְׁלִ֣יךְ",
      "parsingLabel": "verbo hif‘il infinitivo (construct) desconocido desconocido desconocido constructivo",
      "parsing": "VERBO.HIF.INFC.U.U.U.C",
      "traduccion": "lanzar"
    },
    {
      "numero": 4,
      "strongNumber": "68",
      "hebreo": "אֶבֶן",
      "transliteracion": "אֲבָנִ֔ים",
      "parsingLabel": "sustantivo femenino plural absoluto",
      "parsing": "SUBS.F.PL.A",
      "traduccion": "piedras"
    },
    {
      "numero": 5,
      "strongNumber": "9005",
      "hebreo": "וְ",
      "transliteracion": "וְ",
      "parsingLabel": "conjunción",
      "parsing": "CONJ",
      "traduccion": "y"
    },
    {
      "numero": 6,
      "strongNumber": "6256",
      "hebreo": "עֵת",
      "transliteracion": "עֵ֖ת",
      "parsingLabel": "sustantivo desconocido singular constructivo",
      "parsing": "SUBS.U.SG.C",
      "traduccion": "tiempo"
    },
    {
      "numero": 7,
      "strongNumber": "3664",
      "hebreo": "כנס",
      "transliteracion": "כְּנֹ֣וס",
      "parsingLabel": "verbo qal infinitivo (construct) desconocido desconocido desconocido constructivo",
      "parsing": "VERBO.QAL.INFC.U.U.U.C",
      "traduccion": "de amontonar"
    },
    {
      "numero": 8,
      "strongNumber": "68",
      "hebreo": "אֶבֶן",
      "transliteracion": "אֲבָנִ֑ים",
      "parsingLabel": "sustantivo femenino plural absoluto",
      "parsing": "SUBS.F.PL.A",
      "traduccion": ";piedras"
    },
    {
      "numero": 9,
      "strongNumber": "6256",
      "hebreo": "עֵת",
      "transliteracion": "עֵ֣ת",
      "parsingLabel": "sustantivo desconocido singular absoluto",
      "parsing": "SUBS.U.SG.A",
      "traduccion": "tiempo"
    },
    {
      "numero": 10,
      "strongNumber": "9003",
      "hebreo": "לְ",
      "transliteracion": "לַ",
      "parsingLabel": "preposición",
      "parsing": "PREP",
      "traduccion": "para"
    },
    {
      "numero": 11,
      "strongNumber": "2263",
      "hebreo": "חבק",
      "transliteracion": "חֲבֹ֔וק",
      "parsingLabel": "verbo qal infinitivo (construct) desconocido desconocido desconocido absoluto",
      "parsing": "VERBO.QAL.INFC.U.U.U.A",
      "traduccion": "abrazar"
    },
    {
      "numero": 12,
      "strongNumber": "9005",
      "hebreo": "וְ",
      "transliteracion": "וְ",
      "parsingLabel": "conjunción",
      "parsing": "CONJ",
      "traduccion": "y"
    },
    {
      "numero": 13,
      "strongNumber": "6256",
      "hebreo": "עֵת",
      "transliteracion": "עֵ֖ת",
      "parsingLabel": "sustantivo desconocido singular absoluto",
      "parsing": "SUBS.U.SG.A",
      "traduccion": "tiempo"
    },
    {
      "numero": 14,
      "strongNumber": "9003",
      "hebreo": "לְ",
      "transliteracion": "לִ",
      "parsingLabel": "preposición",
      "parsing": "PREP",
      "traduccion": "para"
    },
    {
      "numero": 15,
      "strongNumber": "7368",
      "hebreo": "רחק",
      "transliteracion": "רְחֹ֥ק",
      "parsingLabel": "verbo qal infinitivo (construct) desconocido desconocido desconocido absoluto",
      "parsing": "VERBO.QAL.INFC.U.U.U.A",
      "traduccion": "alejarse"
    },
    {
      "numero": 16,
      "strongNumber": "4480",
      "hebreo": "מִן",
      "transliteracion": "מֵ",
      "parsingLabel": "preposición",
      "parsing": "PREP",
      "traduccion": "de"
    },
    {
      "numero": 17,
      "strongNumber": "2263",
      "hebreo": "חבק",
      "transliteracion": "חַבֵּֽק׃",
      "parsingLabel": "verbo pi“el infinitivo (construct) desconocido desconocido desconocido absoluto",
      "parsing": "VERBO.PIEL.INFC.U.U.U.A",
      "traduccion": "abrazar"
    }
  ]
}