{
  "versiculo": {
    "referencia": "Génesis 30:7 Reina Valera 1960",
    "texto": "Concibió otra vez Bilha la sierva de Raquel, y dio a luz un segundo hijo a Jacob."
  },
  "analisisInterlineal": [
    {
      "numero": 1,
      "strongNumber": "9005",
      "hebreo": "וְ",
      "transliteracion": "וַ",
      "parsingLabel": "conjunción",
      "parsing": "CONJ",
      "traduccion": "Y"
    },
    {
      "numero": 2,
      "strongNumber": "2029",
      "hebreo": "הרה",
      "transliteracion": "תַּ֣הַר",
      "parsingLabel": "verbo qal wayyiqtol 3ª persona femenino singular",
      "parsing": "VERBO.QAL.WAYQ.P3.F.SG",
      "traduccion": "concibió"
    },
    {
      "numero": 3,
      "strongNumber": "5750",
      "hebreo": "עֹוד",
      "transliteracion": "עֹ֔וד",
      "parsingLabel": "adverbio masculino singular absoluto",
      "parsing": "ADVB.M.SG.A",
      "traduccion": "otra vez"
    },
    {
      "numero": 4,
      "strongNumber": "9005",
      "hebreo": "וְ",
      "transliteracion": "וַ",
      "parsingLabel": "conjunción",
      "parsing": "CONJ",
      "traduccion": "y"
    },
    {
      "numero": 5,
      "strongNumber": "3205",
      "hebreo": "ילד",
      "transliteracion": "תֵּ֕לֶד",
      "parsingLabel": "verbo qal wayyiqtol 3ª persona femenino singular",
      "parsing": "VERBO.QAL.WAYQ.P3.F.SG",
      "traduccion": "dio a luz"
    },
    {
      "numero": 6,
      "strongNumber": "1090",
      "hebreo": "בִּלְהָה",
      "transliteracion": "בִּלְהָ֖ה",
      "parsingLabel": "nombre propio femenino singular absoluto",
      "parsing": "NMPR.F.SG.A",
      "traduccion": "Bilha"
    },
    {
      "numero": 7,
      "strongNumber": "8198",
      "hebreo": "שִׁפְחָה",
      "transliteracion": "שִׁפְחַ֣ת",
      "parsingLabel": "sustantivo femenino singular constructivo",
      "parsing": "SUBS.F.SG.C",
      "traduccion": "sierva de"
    },
    {
      "numero": 8,
      "strongNumber": "7354",
      "hebreo": "רָחֵל",
      "transliteracion": "רָחֵ֑ל",
      "parsingLabel": "nombre propio femenino singular absoluto",
      "parsing": "NMPR.F.SG.A",
      "traduccion": "Raquel"
    },
    {
      "numero": 9,
      "strongNumber": "1121",
      "hebreo": "בֵּן",
      "transliteracion": "בֵּ֥ן",
      "parsingLabel": "sustantivo masculino singular absoluto",
      "parsing": "SUBS.M.SG.A",
      "traduccion": "hijo"
    },
    {
      "numero": 10,
      "strongNumber": "8145",
      "hebreo": "שֵׁנִי",
      "transliteracion": "שֵׁנִ֖י",
      "parsingLabel": "adjetivo masculino singular absoluto",
      "parsing": "ADJV.M.SG.A",
      "traduccion": "segundo"
    },
    {
      "numero": 11,
      "strongNumber": "9003",
      "hebreo": "לְ",
      "transliteracion": "לְ",
      "parsingLabel": "preposición",
      "parsing": "PREP",
      "traduccion": "para"
    },
    {
      "numero": 12,
      "strongNumber": "3290",
      "hebreo": "יַעֲקֹב",
      "transliteracion": "יַעֲקֹֽב׃",
      "parsingLabel": "nombre propio masculino singular absoluto",
      "parsing": "NMPR.M.SG.A",
      "traduccion": "Jacob."
    }
  ]
}