{
  "versiculo": {
    "referencia": "Jeremías 7:29 Reina Valera 1960",
    "texto": "Corta tu cabello, y arrójalo, y levanta llanto sobre las alturas; porque Jehová ha aborrecido y dejado la generación objeto de su ira."
  },
  "analisisInterlineal": [
    {
      "numero": 1,
      "strongNumber": "1494",
      "hebreo": "גזז",
      "transliteracion": "גָּזִּ֤י",
      "parsingLabel": "verbo qal imperativo 2ª persona femenino singular",
      "parsing": "VERBO.QAL.IMPV.P2.F.SG",
      "traduccion": "corta"
    },
    {
      "numero": 2,
      "strongNumber": "5145",
      "hebreo": "נֵזֶר",
      "transliteracion": "נִזְרֵךְ֙",
      "parsingLabel": "sustantivo masculino singular absoluto pronominal sufijo 2ª persona femenino singular",
      "parsing": "SUBS.M.SG.A.PRS.P2.F.SG",
      "traduccion": "tu cabello"
    },
    {
      "numero": 3,
      "strongNumber": "9005",
      "hebreo": "וְ",
      "transliteracion": "וְֽ",
      "parsingLabel": "conjunción",
      "parsing": "CONJ",
      "traduccion": "y"
    },
    {
      "numero": 4,
      "strongNumber": "7993",
      "hebreo": "שׁלך",
      "transliteracion": "הַשְׁלִ֔יכִי",
      "parsingLabel": "verbo hif‘il imperativo 2ª persona femenino singular",
      "parsing": "VERBO.HIF.IMPV.P2.F.SG",
      "traduccion": "arrojalo"
    },
    {
      "numero": 5,
      "strongNumber": "9005",
      "hebreo": "וְ",
      "transliteracion": "וּ",
      "parsingLabel": "conjunción",
      "parsing": "CONJ",
      "traduccion": "y"
    },
    {
      "numero": 6,
      "strongNumber": "5375",
      "hebreo": "נשׂא",
      "transliteracion": "שְׂאִ֥י",
      "parsingLabel": "verbo qal imperativo 2ª persona femenino singular",
      "parsing": "VERBO.QAL.IMPV.P2.F.SG",
      "traduccion": "alza"
    },
    {
      "numero": 7,
      "strongNumber": "5921",
      "hebreo": "עַל",
      "transliteracion": "עַל־",
      "parsingLabel": "preposición",
      "parsing": "PREP",
      "traduccion": "sobre"
    },
    {
      "numero": 8,
      "strongNumber": "8205",
      "hebreo": "שְׁפִי",
      "transliteracion": "שְׁפָיִ֖ם",
      "parsingLabel": "sustantivo masculino plural absoluto",
      "parsing": "SUBS.M.PL.A",
      "traduccion": "colinas estériles"
    },
    {
      "numero": 9,
      "strongNumber": "7015",
      "hebreo": "קִינָה",
      "transliteracion": "קִינָ֑ה",
      "parsingLabel": "sustantivo femenino singular absoluto",
      "parsing": "SUBS.F.SG.A",
      "traduccion": "lamento"
    },
    {
      "numero": 10,
      "strongNumber": "3588",
      "hebreo": "כִּי",
      "transliteracion": "כִּ֚י",
      "parsingLabel": "conjunción",
      "parsing": "CONJ",
      "traduccion": "porque"
    },
    {
      "numero": 11,
      "strongNumber": "3988",
      "hebreo": "מאס",
      "transliteracion": "מָאַ֣ס",
      "parsingLabel": "verbo qal perfecto 3ª persona masculino singular",
      "parsing": "VERBO.QAL.PERF.P3.M.SG",
      "traduccion": "rechazó"
    },
    {
      "numero": 12,
      "strongNumber": "3068",
      "hebreo": "יְהוָה",
      "transliteracion": "יְהוָ֔ה",
      "parsingLabel": "nombre propio masculino singular absoluto",
      "parsing": "NMPR.M.SG.A",
      "traduccion": "Yahweh"
    },
    {
      "numero": 13,
      "strongNumber": "9005",
      "hebreo": "וְ",
      "transliteracion": "וַ",
      "parsingLabel": "conjunción",
      "parsing": "CONJ",
      "traduccion": "y"
    },
    {
      "numero": 14,
      "strongNumber": "5203",
      "hebreo": "נטשׁ",
      "transliteracion": "יִּטֹּ֖שׁ",
      "parsingLabel": "verbo qal wayyiqtol 3ª persona masculino singular",
      "parsing": "VERBO.QAL.WAYQ.P3.M.SG",
      "traduccion": "abandonó"
    },
    {
      "numero": 15,
      "strongNumber": "853",
      "hebreo": "אֵת",
      "transliteracion": "אֶת־",
      "parsingLabel": "preposición",
      "parsing": "PREP",
      "traduccion": "a"
    },
    {
      "numero": 16,
      "strongNumber": "1755",
      "hebreo": "דֹּור",
      "transliteracion": "דֹּ֥ור",
      "parsingLabel": "sustantivo masculino singular constructivo",
      "parsing": "SUBS.M.SG.C",
      "traduccion": "generación de"
    },
    {
      "numero": 17,
      "strongNumber": "5678",
      "hebreo": "עֶבְרָה",
      "transliteracion": "עֶבְרָתֹֽו׃",
      "parsingLabel": "sustantivo femenino singular absoluto pronominal sufijo 3ª persona masculino singular",
      "parsing": "SUBS.F.SG.A.PRS.P3.M.SG",
      "traduccion": "su ira"
    }
  ]
}