{
  "versiculo": {
    "referencia": "Oseas 12:8 Reina Valera 1960",
    "texto": "Efraín dijo: Ciertamente he enriquecido, he hallado riquezas para mí; nadie hallará iniquidad en mí, ni pecado en todos mis trabajos."
  },
  "analisisInterlineal": [
    {
      "numero": 1,
      "strongNumber": "9005",
      "hebreo": "וְ",
      "transliteracion": "וַ",
      "parsingLabel": "conjunción",
      "parsing": "CONJ",
      "traduccion": "Y"
    },
    {
      "numero": 2,
      "strongNumber": "559",
      "hebreo": "אמר",
      "transliteracion": "יֹּ֣אמֶר",
      "parsingLabel": "verbo qal wayyiqtol 3ª persona masculino singular",
      "parsing": "VERBO.QAL.WAYQ.P3.M.SG",
      "traduccion": "dijo"
    },
    {
      "numero": 3,
      "strongNumber": "669",
      "hebreo": "אֶפְרַיִם",
      "transliteracion": "אֶפְרַ֔יִם",
      "parsingLabel": "nombre propio desconocido singular absoluto",
      "parsing": "NMPR.U.SG.A",
      "traduccion": "Efraín"
    },
    {
      "numero": 4,
      "strongNumber": "389",
      "hebreo": "אַךְ",
      "transliteracion": "אַ֣ךְ",
      "parsingLabel": "adverbio",
      "parsing": "ADVB",
      "traduccion": ":así"
    },
    {
      "numero": 5,
      "strongNumber": "6238",
      "hebreo": "עשׁר",
      "transliteracion": "עָשַׁ֔רְתִּי",
      "parsingLabel": "verbo qal perfecto 1ª persona desconocido singular",
      "parsing": "VERBO.QAL.PERF.P1.U.SG",
      "traduccion": "Me enriquecí"
    },
    {
      "numero": 6,
      "strongNumber": "4672",
      "hebreo": "מצא",
      "transliteracion": "מָצָ֥אתִי",
      "parsingLabel": "verbo qal perfecto 1ª persona desconocido singular",
      "parsing": "VERBO.QAL.PERF.P1.U.SG",
      "traduccion": "hallé"
    },
    {
      "numero": 7,
      "strongNumber": "202",
      "hebreo": "אֹון",
      "transliteracion": "אֹ֖ון",
      "parsingLabel": "sustantivo masculino singular absoluto",
      "parsing": "SUBS.M.SG.A",
      "traduccion": "riqueza"
    },
    {
      "numero": 8,
      "strongNumber": "9003",
      "hebreo": "לְ",
      "transliteracion": "לִ֑י",
      "parsingLabel": "preposición pronominal sufijo 1ª persona desconocido singular",
      "parsing": "PREP.PRS.P1.U.SG",
      "traduccion": "para mi"
    },
    {
      "numero": 9,
      "strongNumber": "3605",
      "hebreo": "כֹּל",
      "transliteracion": "כָּל־",
      "parsingLabel": "sustantivo masculino singular constructivo",
      "parsing": "SUBS.M.SG.C",
      "traduccion": "todas"
    },
    {
      "numero": 10,
      "strongNumber": "3018",
      "hebreo": "יְגִיעַ",
      "transliteracion": "יְגִיעַ֕י",
      "parsingLabel": "sustantivo masculino plural absoluto",
      "parsing": "SUBS.M.PL.A",
      "traduccion": "mis obras"
    },
    {
      "numero": 11,
      "strongNumber": "3808",
      "hebreo": "לֹא",
      "transliteracion": "לֹ֥א",
      "parsingLabel": "negativo partículo",
      "parsing": "NEGA",
      "traduccion": "no"
    },
    {
      "numero": 12,
      "strongNumber": "4672",
      "hebreo": "מצא",
      "transliteracion": "יִמְצְאוּ־",
      "parsingLabel": "verbo qal imperfecto 3ª persona masculino plural",
      "parsing": "VERBO.QAL.IMPF.P3.M.PL",
      "traduccion": "hallarán"
    },
    {
      "numero": 13,
      "strongNumber": "9003",
      "hebreo": "לְ",
      "transliteracion": "לִ֖י",
      "parsingLabel": "preposición pronominal sufijo 1ª persona desconocido singular",
      "parsing": "PREP.PRS.P1.U.SG",
      "traduccion": "en mi"
    },
    {
      "numero": 14,
      "strongNumber": "5771",
      "hebreo": "עָוֹן",
      "transliteracion": "עָוֹ֥ן",
      "parsingLabel": "sustantivo masculino singular absoluto",
      "parsing": "SUBS.M.SG.A",
      "traduccion": "iniquidad"
    },
    {
      "numero": 15,
      "strongNumber": "834",
      "hebreo": "אֲשֶׁר",
      "transliteracion": "אֲשֶׁר־",
      "parsingLabel": "conjunción",
      "parsing": "CONJ",
      "traduccion": "ni"
    },
    {
      "numero": 16,
      "strongNumber": "2399",
      "hebreo": "חֵטְא",
      "transliteracion": "חֵֽטְא׃",
      "parsingLabel": "sustantivo masculino singular absoluto",
      "parsing": "SUBS.M.SG.A",
      "traduccion": "pecado"
    }
  ]
}